pysistant/__init__.py
pysistant/helpers.py
pysistant/logging.py
tests/__init__.py
tests/test_helpers.py
pysistant-1.0.9.dist-info/LICENSE
pysistant-1.0.9.dist-info/METADATA
pysistant-1.0.9.dist-info/WHEEL
pysistant-1.0.9.dist-info/top_level.txt
pysistant-1.0.9.dist-info/RECORD
