Metadata-Version: 2.1
Name: pysistant
Version: 1.0.9
Summary: The package contains different helpers for speeding up programming on Python.
Home-page: https://github.com/Ilyushin/pysistant
Author: Eugene Ilyushin
Author-email: eugene.ilyushin@gmail.com
Classifier: Programming Language :: Python :: 3
Classifier: License :: OSI Approved :: MIT License
Classifier: Operating System :: OS Independent
License-File: LICENSE
Requires-Dist: numpy
Requires-Dist: pylint
Requires-Dist: setuptools
Requires-Dist: absl-py
